ionoscloud_vm_autoscaling/__init__.py
ionoscloud_vm_autoscaling/api_client.py
ionoscloud_vm_autoscaling/api_response.py
ionoscloud_vm_autoscaling/configuration.py
ionoscloud_vm_autoscaling/exceptions.py
ionoscloud_vm_autoscaling/rest.py
ionoscloud_vm_autoscaling/test-driver.py
ionoscloud_vm_autoscaling/api/__init__.py
ionoscloud_vm_autoscaling/api/auto_scaling_groups_api.py
ionoscloud_vm_autoscaling/api/documentation_api.py
ionoscloud_vm_autoscaling/api/groups_api.py
ionoscloud_vm_autoscaling/models/__init__.py
ionoscloud_vm_autoscaling/models/action.py
ionoscloud_vm_autoscaling/models/action_all_of.py
ionoscloud_vm_autoscaling/models/action_amount.py
ionoscloud_vm_autoscaling/models/action_collection.py
ionoscloud_vm_autoscaling/models/action_collection_all_of.py
ionoscloud_vm_autoscaling/models/action_properties.py
ionoscloud_vm_autoscaling/models/action_resource.py
ionoscloud_vm_autoscaling/models/action_resource_all_of.py
ionoscloud_vm_autoscaling/models/action_status.py
ionoscloud_vm_autoscaling/models/action_type.py
ionoscloud_vm_autoscaling/models/actions_link_resource.py
ionoscloud_vm_autoscaling/models/actions_link_resource_all_of.py
ionoscloud_vm_autoscaling/models/availability_zone.py
ionoscloud_vm_autoscaling/models/bus_type.py
ionoscloud_vm_autoscaling/models/collection.py
ionoscloud_vm_autoscaling/models/collection_all_of.py
ionoscloud_vm_autoscaling/models/cpu_family.py
ionoscloud_vm_autoscaling/models/datacenter_server.py
ionoscloud_vm_autoscaling/models/datacenter_server_all_of.py
ionoscloud_vm_autoscaling/models/error.py
ionoscloud_vm_autoscaling/models/error401.py
ionoscloud_vm_autoscaling/models/error401_all_of.py
ionoscloud_vm_autoscaling/models/error401_message.py
ionoscloud_vm_autoscaling/models/error401_message_all_of.py
ionoscloud_vm_autoscaling/models/error404.py
ionoscloud_vm_autoscaling/models/error404_all_of.py
ionoscloud_vm_autoscaling/models/error404_message.py
ionoscloud_vm_autoscaling/models/error404_message_all_of.py
ionoscloud_vm_autoscaling-1.0.1.dist-info/LICENSE
ionoscloud_vm_autoscaling-1.0.1.dist-info/METADATA
ionoscloud_vm_autoscaling-1.0.1.dist-info/WHEEL
ionoscloud_vm_autoscaling-1.0.1.dist-info/top_level.txt
ionoscloud_vm_autoscaling-1.0.1.dist-info/RECORD
